handytools/__init__.py
handytools/settings.py
handytools/contact/__init__.py
handytools/contact/admin.py
handytools/contact/apps.py
handytools/contact/migrations/0001_initial.py
handytools/contact/migrations/__init__.py
handytools/contact/models/__init__.py
handytools/contact/models/models.py
handytools/handyutils/__init__.py
handytools/handyutils/admin.py
handytools/handyutils/apps.py
handytools/handyutils/migrations/__init__.py
handytools/handyutils/templatetags/__init__.py
handytools/handyutils/templatetags/google_analytic.py
handytools/handyutils/templatetags/link_creators.py
handytools/handyutils/templatetags/nodes.py
handytools/textimagephrase/__init__.py
handytools/textimagephrase/admin.py
handytools/textimagephrase/apps.py
handytools/textimagephrase/forms.py
handytools/textimagephrase/migrations/0001_initial.py
handytools/textimagephrase/migrations/__init__.py
handytools/textimagephrase/models/__init__.py
handytools/textimagephrase/models/models.py
handytools/textphrase/__init__.py
handytools/textphrase/admin.py
handytools/textphrase/apps.py
handytools/textphrase/forms.py
handytools/textphrase/context_processors/__init__.py
handytools/textphrase/context_processors/text_phrase_cps.py
handytools/textphrase/migrations/0001_initial.py
handytools/textphrase/migrations/__init__.py
handytools/textphrase/models/__init__.py
handytools/textphrase/models/models.py
handytools/textphrase/templatetags/__init__.py
handytools/textphrase/templatetags/phrases_tags.py
django_handytools-0.3.1.dist-info/LICENSE
django_handytools-0.3.1.dist-info/METADATA
django_handytools-0.3.1.dist-info/WHEEL
django_handytools-0.3.1.dist-info/top_level.txt
django_handytools-0.3.1.dist-info/RECORD
